LICENSE
README.md
setup.py
test_whisper.py
whisper.py
bin/find-corrupt-whisper-files.py
bin/rrd2whisper.py
bin/whisper-create.py
bin/whisper-diff.py
bin/whisper-dump.py
bin/whisper-fetch.py
bin/whisper-fill.py
bin/whisper-info.py
bin/whisper-merge.py
bin/whisper-resize.py
bin/whisper-set-aggregation-method.py
bin/whisper-set-xfilesfactor.py
bin/whisper-update.py
contrib/update-storage-times.py
contrib/whisper-auto-resize.py
contrib/whisper-auto-update.py
whisper.egg-info/PKG-INFO
whisper.egg-info/SOURCES.txt
whisper.egg-info/dependency_links.txt
whisper.egg-info/not-zip-safe
whisper.egg-info/requires.txt
whisper.egg-info/top_level.txt