Metadata-Version: 2.1
Name: whisper
Version: 1.1.9
Summary: Fixed size round-robin style database
Home-page: http://graphiteapp.org/
Author: Chris Davis
Author-email: chrismd@gmail.com
License: Apache Software License 2.0
Classifier: Programming Language :: Python :: 2
Classifier: Programming Language :: Python :: 2.7
Classifier: Programming Language :: Python :: 3
Classifier: Programming Language :: Python :: 3.5
Classifier: Programming Language :: Python :: 3.6
Classifier: Programming Language :: Python :: 3.7
Classifier: Programming Language :: Python :: Implementation :: CPython
Classifier: Programming Language :: Python :: Implementation :: PyPy
License-File: LICENSE
